safeai/__init__.py
safeai/losses/__init__.py
safeai/metrics/__init__.py
safeai/models/__init__.py
safeai/models/identity.py
safeai/models/lenet.py
safeai/models/matmul.py
safeai/models/sample_model.py
safeai-0.0.2.dist-info/METADATA
safeai-0.0.2.dist-info/RECORD
safeai-0.0.2.dist-info/WHEEL
safeai-0.0.2.dist-info/top_level.txt
