Metadata-Version: 2.1
Name: safeai
Version: 0.0.2
Summary: SafeAI
Home-page: https://github.com/EpisysScience/SafeAI
Author: Episys Science
Author-email: sangsulee92@gmail.com
License: UNKNOWN
Platform: UNKNOWN
Classifier: Programming Language :: Python :: 3 :: Only
